crmeta/__init__.py
crmeta/admin.py
crmeta/apps.py
crmeta/models.py
crmeta/tests.py
crmeta/views.py
crmeta-0.0.1.dist-info/LICENSE
crmeta-0.0.1.dist-info/METADATA
crmeta-0.0.1.dist-info/WHEEL
crmeta-0.0.1.dist-info/top_level.txt
crmeta-0.0.1.dist-info/RECORD
